cpremote/__init__.py
cpremote/cpremote.py
cpremote-1.0.3.dist-info/LICENSE.md
cpremote-1.0.3.dist-info/METADATA
cpremote-1.0.3.dist-info/WHEEL
cpremote-1.0.3.dist-info/entry_points.txt
cpremote-1.0.3.dist-info/top_level.txt
cpremote-1.0.3.dist-info/RECORD
