Metadata-Version: 2.1
Name: cpremote
Version: 1.0.3
Summary: cpremote is a command line tool for interacting with a CircuitPython remote filesystem access using the web based workflow
Author-email: dzlucha <dszlucha@duck.com>
License: MIT License
Project-URL: Homepage, https://github.com/dszlucha/cpremote
Project-URL: Issues, https://github.com/dszlucha/cpremote/issues
Keywords: CircuitPython
Classifier: Programming Language :: Python :: 3
Classifier: License :: OSI Approved :: MIT License
Classifier: Operating System :: OS Independent
Requires-Python: >=3.9
License-File: LICENSE.md
Requires-Dist: python-dotenv
Requires-Dist: requests
